README.md
setup.cfg
setup.py
pyflakes_ext/__init__.py
pyflakes_ext/pyflakes_ext.py
pyflakes_ext.egg-info/PKG-INFO
pyflakes_ext.egg-info/SOURCES.txt
pyflakes_ext.egg-info/dependency_links.txt
pyflakes_ext.egg-info/entry_points.txt
pyflakes_ext.egg-info/requires.txt
pyflakes_ext.egg-info/top_level.txt