Metadata-Version: 1.0
Name: pyflakes-ext
Version: 2.0.0
Summary: A few extra additions to pyflakes.
Home-page: https://github.com/qntln/pyflakes-ext
Author: Quantlane
Author-email: code@quantlane.com
License: MIT
Platform: UNKNOWN
